COPYING
COPYING.lesser
MANIFEST.in
NOTICE
README.md
requirements.txt
setup.py
Loligram.egg-info/PKG-INFO
Loligram.egg-info/SOURCES.txt
Loligram.egg-info/dependency_links.txt
Loligram.egg-info/not-zip-safe
Loligram.egg-info/requires.txt
Loligram.egg-info/top_level.txt
compiler/__init__.py
compiler/api/__init__.py
compiler/api/compiler.py
compiler/api/source/auth_key.tl
compiler/api/source/main_api.tl
compiler/api/source/main_api_old.tl
compiler/api/source/sys_msgs.tl
compiler/api/template/combinator.txt
compiler/api/template/type.txt
compiler/docs/__init__.py
compiler/docs/compiler.py
compiler/docs/template/page.txt
compiler/docs/template/toctree.txt
compiler/errors/__init__.py
compiler/errors/compiler.py
compiler/errors/sort.py
compiler/errors/source/303_SEE_OTHER.tsv
compiler/errors/source/400_BAD_REQUEST.tsv
compiler/errors/source/401_UNAUTHORIZED.tsv
compiler/errors/source/403_FORBIDDEN.tsv
compiler/errors/source/406_NOT_ACCEPTABLE.tsv
compiler/errors/source/420_FLOOD.tsv
compiler/errors/source/500_INTERNAL_SERVER_ERROR.tsv
compiler/errors/source/503_SERVICE_UNAVAILABLE.tsv
compiler/errors/template/class.txt
compiler/errors/template/sub_class.txt
loligram/__init__.py
loligram/client.py
loligram/dispatcher.py
loligram/emoji.py
loligram/file_id.py
loligram/filters.py
loligram/mime_types.py
loligram/py.typed
loligram/sync.py
loligram/utils.py
loligram/connection/__init__.py
loligram/connection/connection.py
loligram/connection/transport/__init__.py
loligram/connection/transport/tcp/__init__.py
loligram/connection/transport/tcp/tcp.py
loligram/connection/transport/tcp/tcp_abridged.py
loligram/connection/transport/tcp/tcp_abridged_o.py
loligram/connection/transport/tcp/tcp_full.py
loligram/connection/transport/tcp/tcp_intermediate.py
loligram/connection/transport/tcp/tcp_intermediate_o.py
loligram/crypto/__init__.py
loligram/crypto/aes.py
loligram/crypto/mtproto.py
loligram/crypto/prime.py
loligram/crypto/rsa.py
loligram/enums/__init__.py
loligram/enums/auto_name.py
loligram/enums/chat_action.py
loligram/enums/chat_event_action.py
loligram/enums/chat_member_status.py
loligram/enums/chat_members_filter.py
loligram/enums/chat_type.py
